cortex/__init__.py
cortex/core.py
cortex/oas_integration.py
cortex/layers/__init__.py
cortex/layers/layer1.py
cortex/layers/layer2.py
cortex/layers/layer3.py
cortex/layers/onnx_models.py
cortex_intelligence-0.1.0.dist-info/licenses/LICENSE
cortex_intelligence-0.1.0.dist-info/METADATA
cortex_intelligence-0.1.0.dist-info/WHEEL
cortex_intelligence-0.1.0.dist-info/top_level.txt
cortex_intelligence-0.1.0.dist-info/RECORD
