Metadata-Version: 2.4
Name: cortex-intelligence
Version: 0.1.0
Summary: A three-layer intelligence engine with ONNX integration for Open Agent Spec
Author-email: Andrew Whitehouse <andrew@primevector.com.au>
License-Expression: MIT
Project-URL: Homepage, https://github.com/prime-vector/cortex
Project-URL: Repository, https://github.com/prime-vector/cortex
Project-URL: Documentation, https://github.com/prime-vector/cortex#readme
Project-URL: Bug Tracker, https://github.com/prime-vector/cortex/issues
Keywords: ai,intelligence,onnx,open-agent-spec,machine-learning,neural-networks
Classifier: Development Status :: 4 - Beta
Classifier: Intended Audience :: Developers
Classifier: Intended Audience :: Science/Research
Classifier: Programming Language :: Python :: 3
Classifier: Programming Language :: Python :: 3.8
Classifier: Programming Language :: Python :: 3.9
Classifier: Programming Language :: Python :: 3.10
Classifier: Programming Language :: Python :: 3.11
Classifier: Programming Language :: Python :: 3.12
Classifier: Topic :: Scientific/Engineering :: Artificial Intelligence
Classifier: Topic :: Software Development :: Libraries :: Python Modules
Classifier: Topic :: System :: Distributed Computing
Requires-Python: >=3.8
License-File: LICENSE
Requires-Dist: numpy>=1.21.0
Requires-Dist: onnxruntime>=1.12.0
Requires-Dist: pillow>=9.0.0
Requires-Dist: requests>=2.28.0
Requires-Dist: aiohttp>=3.8.0
Requires-Dist: pydantic>=1.10.0
Provides-Extra: dev
Requires-Dist: pytest>=7.0.0; extra == "dev"
Requires-Dist: pytest-asyncio>=0.21.0; extra == "dev"
Requires-Dist: black>=22.0.0; extra == "dev"
Requires-Dist: flake8>=5.0.0; extra == "dev"
Requires-Dist: mypy>=0.991; extra == "dev"
Dynamic: license-file
